{
  "collectionName": "components_shared_buttons",
  "info": {
    "name": "Button",
    "icon": "arrow-alt-circle-down"
  },
  "options": {},
  "attributes": {
    "text": {
      "type": "string",
      "required": true,
      "minLength": 2
    },
    "type": {
      "type": "enumeration",
      "enum": [
        "button",
        "submit",
        "reset"
      ],
      "required": true,
      "default": "submit"
    },
    "disabled": {
      "type": "boolean",
      "default": false
    }
  }
}
