{"namedChunkGroups":{"polyfill":{"name":"polyfill","assets":[{"name":"polyfill.js","size":998509},{"name":"polyfill.0c1a69cecceff5313cb8.hot-update.js","size":875}],"filteredAssets":0,"assetsSize":999384,"filteredAuxiliaryAssets":0,"auxiliaryAssetsSize":0},"commons":{"name":"commons","assets":[{"name":"framework.js","size":2669340},{"name":"commons.css","size":169635},{"name":"commons.js","size":3168695},{"name":"commons.0c1a69cecceff5313cb8.hot-update.js","size":2547}],"filteredAssets":0,"assetsSize":6010217,"filteredAuxiliaryAssets":0,"auxiliaryAssetsSize":0},"component---cache-dev-404-page-js":{"name":"component---cache-dev-404-page-js","assets":[{"name":"component---cache-dev-404-page-js.js","size":67087}],"filteredAssets":0,"assetsSize":67087,"filteredAuxiliaryAssets":0,"auxiliaryAssetsSize":0},"component---src-pages-404-js":{"name":"component---src-pages-404-js","assets":[{"name":"component---src-pages-404-js.js","size":221174}],"filteredAssets":0,"assetsSize":221174,"filteredAuxiliaryAssets":0,"auxiliaryAssetsSize":0},"component---src-pages-index-js":{"name":"component---src-pages-index-js","assets":[{"name":"framework.js","size":2669340},{"name":"commons.css","size":169635},{"name":"commons.js","size":3168695},{"name":"commons.0c1a69cecceff5313cb8.hot-update.js","size":2547},{"name":"component---src-pages-index-js.js","size":221828},{"name":"component---src-pages-index-js.0c1a69cecceff5313cb8.hot-update.js","size":2390}],"filteredAssets":0,"assetsSize":6234435,"filteredAuxiliaryAssets":0,"auxiliaryAssetsSize":0},"component---src-pages-palvelut-js":{"name":"component---src-pages-palvelut-js","assets":[{"name":"framework.js","size":2669340},{"name":"commons.css","size":169635},{"name":"commons.js","size":3168695},{"name":"commons.0c1a69cecceff5313cb8.hot-update.js","size":2547},{"name":"component---src-pages-palvelut-js.js","size":253989},{"name":"component---src-pages-palvelut-js.0c1a69cecceff5313cb8.hot-update.js","size":2393}],"filteredAssets":0,"assetsSize":6266599,"filteredAuxiliaryAssets":0,"auxiliaryAssetsSize":0},"component---src-pages-referenssit-index-js":{"name":"component---src-pages-referenssit-index-js","assets":[{"name":"framework.js","size":2669340},{"name":"commons.css","size":169635},{"name":"commons.js","size":3168695},{"name":"commons.0c1a69cecceff5313cb8.hot-update.js","size":2547},{"name":"component---src-pages-referenssit-index-js.js","size":236295},{"name":"component---src-pages-referenssit-index-js.0c1a69cecceff5313cb8.hot-update.js","size":2402}],"filteredAssets":0,"assetsSize":6248914,"filteredAuxiliaryAssets":0,"auxiliaryAssetsSize":0},"component---src-pages-referenssit-strapi-reference-slug-js":{"name":"component---src-pages-referenssit-strapi-reference-slug-js","assets":[{"name":"component---src-pages-referenssit-strapi-reference-slug-js.js","size":846441}],"filteredAssets":0,"assetsSize":846441,"filteredAuxiliaryAssets":0,"auxiliaryAssetsSize":0},"component---src-pages-tyopaikat-js":{"name":"component---src-pages-tyopaikat-js","assets":[{"name":"framework.js","size":2669340},{"name":"commons.css","size":169635},{"name":"commons.js","size":3168695},{"name":"commons.0c1a69cecceff5313cb8.hot-update.js","size":2547},{"name":"component---src-pages-tyopaikat-js.js","size":228576},{"name":"component---src-pages-tyopaikat-js.0c1a69cecceff5313cb8.hot-update.js","size":2394}],"filteredAssets":0,"assetsSize":6241187,"filteredAuxiliaryAssets":0,"auxiliaryAssetsSize":0},"component---src-pages-yhteystiedot-js":{"name":"component---src-pages-yhteystiedot-js","assets":[{"name":"framework.js","size":2669340},{"name":"commons.css","size":169635},{"name":"commons.js","size":3168695},{"name":"commons.0c1a69cecceff5313cb8.hot-update.js","size":2547},{"name":"component---src-pages-yhteystiedot-js.js","size":280498},{"name":"component---src-pages-yhteystiedot-js.0c1a69cecceff5313cb8.hot-update.js","size":2397}],"filteredAssets":0,"assetsSize":6293112,"filteredAuxiliaryAssets":0,"auxiliaryAssetsSize":0},"component---src-pages-yrityksille-js":{"name":"component---src-pages-yrityksille-js","assets":[{"name":"framework.js","size":2669340},{"name":"commons.css","size":169635},{"name":"commons.js","size":3168695},{"name":"commons.0c1a69cecceff5313cb8.hot-update.js","size":2547},{"name":"component---src-pages-yrityksille-js.js","size":221853},{"name":"component---src-pages-yrityksille-js.0c1a69cecceff5313cb8.hot-update.js","size":2396}],"filteredAssets":0,"assetsSize":6234466,"filteredAuxiliaryAssets":0,"auxiliaryAssetsSize":0}},"assetsByChunkName":{"polyfill":["polyfill.js","polyfill.0c1a69cecceff5313cb8.hot-update.js"],"commons":["framework.js","commons.css","commons.js","commons.0c1a69cecceff5313cb8.hot-update.js"],"component---cache-dev-404-page-js":["component---cache-dev-404-page-js.js"],"component---src-pages-404-js":["component---src-pages-404-js.js"],"component---src-pages-index-js":["framework.js","commons.css","commons.js","commons.0c1a69cecceff5313cb8.hot-update.js","component---src-pages-index-js.js","component---src-pages-index-js.0c1a69cecceff5313cb8.hot-update.js"],"component---src-pages-palvelut-js":["framework.js","commons.css","commons.js","commons.0c1a69cecceff5313cb8.hot-update.js","component---src-pages-palvelut-js.js","component---src-pages-palvelut-js.0c1a69cecceff5313cb8.hot-update.js"],"component---src-pages-referenssit-index-js":["framework.js","commons.css","commons.js","commons.0c1a69cecceff5313cb8.hot-update.js","component---src-pages-referenssit-index-js.js","component---src-pages-referenssit-index-js.0c1a69cecceff5313cb8.hot-update.js"],"component---src-pages-referenssit-strapi-reference-slug-js":["component---src-pages-referenssit-strapi-reference-slug-js.js"],"component---src-pages-tyopaikat-js":["framework.js","commons.css","commons.js","commons.0c1a69cecceff5313cb8.hot-update.js","component---src-pages-tyopaikat-js.js","component---src-pages-tyopaikat-js.0c1a69cecceff5313cb8.hot-update.js"],"component---src-pages-yhteystiedot-js":["framework.js","commons.css","commons.js","commons.0c1a69cecceff5313cb8.hot-update.js","component---src-pages-yhteystiedot-js.js","component---src-pages-yhteystiedot-js.0c1a69cecceff5313cb8.hot-update.js"],"component---src-pages-yrityksille-js":["framework.js","commons.css","commons.js","commons.0c1a69cecceff5313cb8.hot-update.js","component---src-pages-yrityksille-js.js","component---src-pages-yrityksille-js.0c1a69cecceff5313cb8.hot-update.js"]},"childAssetsByChunkName":{}}